tusk/__init__.py
tusk/app.py
tusk/auto_save.py
tusk/cli.py
tusk_editor-0.1.1.dist-info/LICENSE
tusk_editor-0.1.1.dist-info/METADATA
tusk_editor-0.1.1.dist-info/WHEEL
tusk_editor-0.1.1.dist-info/entry_points.txt
tusk_editor-0.1.1.dist-info/RECORD
