Metadata-Version: 2.1
Name: tusk-editor
Version: 0.1.1
Summary: A modern terminal-based Markdown editor
License: MIT
Author: vedant-asati03
Author-email: vedant.asati03@gmail.com
Requires-Python: >=3.12,<4.0
Classifier: License :: OSI Approved :: MIT License
Classifier: Programming Language :: Python :: 3
Classifier: Programming Language :: Python :: 3.12
Requires-Dist: markdown (>=3.5.2,<4.0.0)
Requires-Dist: pygments (>=2.17.2,<3.0.0)
Requires-Dist: pypandoc (>=1.13,<2.0)
Requires-Dist: textual (>=0.86.1,<0.87.0)
